weather/__init__.py
weather/cli.py
weather/weather.py
weathersnake-0.0.7.dist-info/METADATA
weathersnake-0.0.7.dist-info/RECORD
weathersnake-0.0.7.dist-info/WHEEL
weathersnake-0.0.7.dist-info/entry_points.txt
weathersnake-0.0.7.dist-info/top_level.txt
