Metadata-Version: 2.1
Name: weathersnake
Version: 0.0.7
Summary: Python tool to find the weather
Home-page: UNKNOWN
Author: Eric Cheatham
Author-email: UNKNOWN
License: UNKNOWN
Platform: UNKNOWN
Requires-Dist: googlemaps
Requires-Dist: requests[security]
